MANIFEST.in
README.rst
requirements.txt
setup.cfg
setup.py
djmicrosip_mensajesdocumentos/__init__.py
djmicrosip_mensajesdocumentos/__init__.pyc
djmicrosip_mensajesdocumentos/config.pyc
djmicrosip_mensajesdocumentos/forms.pyc
djmicrosip_mensajesdocumentos/models.pyc
djmicrosip_mensajesdocumentos/urls.pyc
djmicrosip_mensajesdocumentos/views.pyc
djmicrosip_mensajesdocumentos.egg-info/PKG-INFO
djmicrosip_mensajesdocumentos.egg-info/SOURCES.txt
djmicrosip_mensajesdocumentos.egg-info/dependency_links.txt
djmicrosip_mensajesdocumentos.egg-info/requires.txt
djmicrosip_mensajesdocumentos.egg-info/top_level.txt
djmicrosip_mensajesdocumentos/custom_db/__init__.py
djmicrosip_mensajesdocumentos/custom_db/__init__.pyc
djmicrosip_mensajesdocumentos/custom_db/punto_venta/__init__.py
djmicrosip_mensajesdocumentos/custom_db/punto_venta/__init__.pyc
djmicrosip_mensajesdocumentos/custom_db/punto_venta/procedures.pyc
djmicrosip_mensajesdocumentos/custom_db/punto_venta/report_builder.pyc
djmicrosip_mensajesdocumentos/custom_db/punto_venta/sql_queries.pyc
djmicrosip_mensajesdocumentos/custom_db/ventas/__init__.py
djmicrosip_mensajesdocumentos/custom_db/ventas/__init__.pyc
djmicrosip_mensajesdocumentos/custom_db/ventas/procedures.pyc
djmicrosip_mensajesdocumentos/custom_db/ventas/sql_queries.pyc
djmicrosip_mensajesdocumentos/templates/djmicrosip_mensajesdocumentos/base.html
djmicrosip_mensajesdocumentos/templates/djmicrosip_mensajesdocumentos/index.html
djmicrosip_mensajesdocumentos/templates/djmicrosip_mensajesdocumentos/preferencias.html